github_manager/__init__.py
github_manager/main.py
github_repo_manager_jkn-1.0.0.dist-info/licenses/LICENSE
github_repo_manager_jkn-1.0.0.dist-info/METADATA
github_repo_manager_jkn-1.0.0.dist-info/WHEEL
github_repo_manager_jkn-1.0.0.dist-info/entry_points.txt
github_repo_manager_jkn-1.0.0.dist-info/top_level.txt
github_repo_manager_jkn-1.0.0.dist-info/RECORD
