Metadata-Version: 2.4
Name: github-repo-manager-jkn
Version: 1.0.0
Summary: Un outil professionnel pour créer et gérer des dépôts GitHub
Home-page: https://github.com/JonathanK-N/github-manager-pro
Author: Jonathan K-N
Author-email: Jonathan K-N <your.email@example.com>
License: MIT
Project-URL: Homepage, https://github.com/JonathanK-N/github-manager-pro
Project-URL: Repository, https://github.com/JonathanK-N/github-manager-pro
Classifier: Development Status :: 5 - Production/Stable
Classifier: Intended Audience :: Developers
Classifier: License :: OSI Approved :: MIT License
Classifier: Programming Language :: Python :: 3
Classifier: Operating System :: OS Independent
Requires-Python: >=3.7
License-File: LICENSE
Requires-Dist: requests>=2.25.0
Dynamic: author
Dynamic: home-page
Dynamic: license-file
Dynamic: requires-python
